backpack/__init__.py
backpack/context.py
backpack/core/__init__.py
backpack/core/derivatives/__init__.py
backpack/core/derivatives/adaptive_avg_pool_nd.py
backpack/core/derivatives/avgpool1d.py
backpack/core/derivatives/avgpool2d.py
backpack/core/derivatives/avgpool3d.py
backpack/core/derivatives/avgpoolnd.py
backpack/core/derivatives/basederivatives.py
backpack/core/derivatives/batchnorm_nd.py
backpack/core/derivatives/bcewithlogitsloss.py
backpack/core/derivatives/conv1d.py
backpack/core/derivatives/conv2d.py
backpack/core/derivatives/conv3d.py
backpack/core/derivatives/conv_transpose1d.py
backpack/core/derivatives/conv_transpose2d.py
backpack/core/derivatives/conv_transpose3d.py
backpack/core/derivatives/conv_transposend.py
backpack/core/derivatives/convnd.py
backpack/core/derivatives/crossentropyloss.py
backpack/core/derivatives/dropout.py
backpack/core/derivatives/elementwise.py
backpack/core/derivatives/elu.py
backpack/core/derivatives/embedding.py
backpack/core/derivatives/flatten.py
backpack/core/derivatives/leakyrelu.py
backpack/core/derivatives/linear.py
backpack/core/derivatives/logsigmoid.py
backpack/core/derivatives/lstm.py
backpack/core/derivatives/maxpool1d.py
backpack/core/derivatives/maxpool2d.py
backpack/core/derivatives/maxpool3d.py
backpack/core/derivatives/maxpoolnd.py
backpack/core/derivatives/mseloss.py
backpack/core/derivatives/nll_base.py
backpack/core/derivatives/pad.py
backpack/core/derivatives/permute.py
backpack/core/derivatives/relu.py
backpack/core/derivatives/rnn.py
backpack/core/derivatives/scale_module.py
backpack/core/derivatives/selu.py
backpack/core/derivatives/shape_check.py
backpack/core/derivatives/sigmoid.py
backpack/core/derivatives/slicing.py
backpack/core/derivatives/sum_module.py
backpack/core/derivatives/tanh.py
backpack/core/derivatives/zeropad2d.py
backpack/custom_module/__init__.py
backpack/custom_module/branching.py
backpack/custom_module/graph_utils.py
backpack/custom_module/pad.py
backpack/custom_module/permute.py
backpack_for_pytorch-1.7.1.dist-info/LICENSE.txt
backpack_for_pytorch-1.7.1.dist-info/METADATA
backpack_for_pytorch-1.7.1.dist-info/WHEEL
backpack_for_pytorch-1.7.1.dist-info/top_level.txt
backpack_for_pytorch-1.7.1.dist-info/RECORD
