Metadata-Version: 2.1
Name: backpack-for-pytorch
Version: 1.7.1
Summary: BackPACK: Packing more into backprop
Author: Felix Dangel, Frederik Kunstner
License: MIT
Project-URL: Repository, https://github.com/f-dangel/backpack
Classifier: Development Status :: 4 - Beta
Classifier: License :: OSI Approved :: MIT License
Classifier: Operating System :: OS Independent
Classifier: Programming Language :: Python :: 3.9
Classifier: Programming Language :: Python :: 3.10
Classifier: Programming Language :: Python :: 3.11
Classifier: Programming Language :: Python :: 3.12
Requires-Python: >=3.9
License-File: LICENSE.txt
Requires-Dist: torch >=2.2.0
Requires-Dist: torchvision >=0.7.0
Requires-Dist: einops <1.0.0,>=0.3.0
Requires-Dist: unfoldNd <1.0.0,>=0.2.0
Provides-Extra: docs
Requires-Dist: matplotlib ; extra == 'docs'
Requires-Dist: sphinx <7 ; extra == 'docs'
Requires-Dist: sphinx-gallery ; extra == 'docs'
Requires-Dist: sphinx-rtd-theme ; extra == 'docs'
Requires-Dist: memory-profiler ; extra == 'docs'
Requires-Dist: tabulate ; extra == 'docs'
Provides-Extra: lint
Requires-Dist: black ; extra == 'lint'
Requires-Dist: flake8 ; extra == 'lint'
Requires-Dist: mccabe ; extra == 'lint'
Requires-Dist: pycodestyle ; extra == 'lint'
Requires-Dist: pyflakes ; extra == 'lint'
Requires-Dist: pep8-naming ; extra == 'lint'
Requires-Dist: flake8-bugbear ; extra == 'lint'
Requires-Dist: flake8-comprehensions ; extra == 'lint'
Requires-Dist: flake8-tidy-imports ; extra == 'lint'
Requires-Dist: darglint ; extra == 'lint'
Requires-Dist: pydocstyle ; extra == 'lint'
Requires-Dist: isort ; extra == 'lint'
Provides-Extra: test
Requires-Dist: scipy ; extra == 'test'
Requires-Dist: numpy <2 ; extra == 'test'
Requires-Dist: pytest <5.0.0,>=4.5.0 ; extra == 'test'
Requires-Dist: pytest-benchmark <4.0.0,>=3.2.2 ; extra == 'test'
Requires-Dist: pytest-optional-tests >=0.1.1 ; extra == 'test'
Requires-Dist: pytest-cov ; extra == 'test'
Requires-Dist: coveralls ; extra == 'test'
